expyta/__init__.py
expyta/common.py
expyta/expyta.py
expyta-0.0.2.dist-info/AUTHORS.rst
expyta-0.0.2.dist-info/LICENSE
expyta-0.0.2.dist-info/METADATA
expyta-0.0.2.dist-info/WHEEL
expyta-0.0.2.dist-info/entry_points.txt
expyta-0.0.2.dist-info/top_level.txt
expyta-0.0.2.dist-info/RECORD
