Metadata-Version: 2.1
Name: expyta
Version: 0.0.2
Summary: Expyta is a streamlined Python library that provides unified access to Taiwanese stock exchange APIs., designed for traders and developers.
Author-email: Thomas Lin <thomaslin@tradinglab.app>
License: MIT License
Project-URL: Homepage, https://github.com/TradingLab-app/expyta
Keywords: expyta
Classifier: Intended Audience :: Developers
Classifier: License :: OSI Approved :: MIT License
Classifier: Natural Language :: English
Classifier: Programming Language :: Python :: 3.8
Classifier: Programming Language :: Python :: 3.9
Classifier: Programming Language :: Python :: 3.10
Classifier: Programming Language :: Python :: 3.11
Classifier: Programming Language :: Python :: 3.12
Requires-Python: >=3.8
License-File: LICENSE
License-File: AUTHORS.rst
Requires-Dist: numpy
Provides-Extra: all
Requires-Dist: expyta[extra] ; extra == 'all'
Provides-Extra: extra
Requires-Dist: pandas ; extra == 'extra'
